JsonOperate/__init__.py
JsonOperate/__main__.py
JsonOperate/function/__init__.py
JsonOperate/function/collect_case_info/__init__.py
JsonOperate/function/collect_case_info/all_case_info.py
JsonOperate/function/collect_case_info/base_info.py
JsonOperate/function/collect_case_info/basic_define.py
JsonOperate/function/collect_case_info/cell_info.py
JsonOperate/function/collect_case_info/collect_case_info.py
JsonOperate/function/collect_case_info/user_info.py
JsonOperate/function/find_case_list/__init__.py
JsonOperate/function/find_case_list/find_list.py
JsonOperate/function/find_case_list/find_list_by_panda.py
JsonOperate/function/print_case_info/__init__.py
JsonOperate/function/print_case_info/print_case_info.py
JsonOperate/function/split_json_structure/__init__.py
JsonOperate/function/split_json_structure/split_json_structure.py
JsonOperate/lib/__init__.py
JsonOperate/lib/excel.py
JsonOperate/lib/input.py
JsonOperate/lib/output.py
JsonOperate/lib/panda_processing.py
JsonOperate/lib/replace_schema.py
JsonOperate/manage/__init__.py
JsonOperate/manage/collect_json_structure_entry.py
JsonOperate/manage/find_case_list_entry.py
JsonOperate/manage/manage.py
JsonOperate/manage/print_all_info_entry.py
JsonOperate/manage/sort_argument.py
JsonOperate/task/__init__.py
JsonOperate/task/add_key_value.py
JsonOperate/task/copy_key_value.py
JsonOperate/task/get_json_info.py
JsonOperate/task/move_key_value.py
JsonOperate/task/remove_key_value.py
JsonOperate/task/value_change.py
JsonOperate/tests/HipTD_THOR_56_CAP6_FDD_32x4RX_10MHz_COMP.json
JsonOperate/tests/HipTD_THOR_56_CAP6_FDD_32x4RX_10MHz_COMP_1.json
JsonOperate/tests/HipTD_THOR_56_CAP6_FDD_32x4RX_10MHz_COMP_add_1.json
JsonOperate/tests/HipTD_THOR_56_CAP6_FDD_32x4RX_10MHz_COMP_move_1.json
JsonOperate/tests/HipTD_THOR_56_CAP6_FDD_32x4RX_10MHz_COMP_remove_1.json
JsonOperate/tests/HipTD_thor_valid_srs_tdd_bwv_CB008322_G_frCfg1208_td_jumping_trigger_snapshot.json
JsonOperate-1.0.1.dist-info/METADATA
JsonOperate-1.0.1.dist-info/WHEEL
JsonOperate-1.0.1.dist-info/top_level.txt
JsonOperate-1.0.1.dist-info/RECORD
