Metadata-Version: 2.1
Name: JsonOperate
Version: 1.0.1
Summary: This wheel is primarily designed for modifying JSON elements.
Home-page: https://gitlab.l1.nsn-net.net/rawu/Json-Operate
Author: ramon Wu
Author-email: ramon.wu@nokia-sbell.com
Requires-Python: >=3.8.0
Requires-Dist: jsonpath-ng==1.6.0
Requires-Dist: numpy==1.24.3
Requires-Dist: pandas==1.4.0
Requires-Dist: openpyxl==3.0.9
